flask_vite-0.6.1.dist-info/METADATA
flask_vite-0.6.1.dist-info/WHEEL
flask_vite-0.6.1.dist-info/entry_points.txt
flask_vite-0.6.1.dist-info/licenses/LICENSE
flask_vite/.idea/.gitignore
flask_vite/.idea/encodings.xml
flask_vite/.idea/flask_vite.iml
flask_vite/.idea/inspectionProfiles/Project_Default.xml
flask_vite/.idea/inspectionProfiles/profiles_settings.xml
flask_vite/.idea/misc.xml
flask_vite/.idea/modules.xml
flask_vite/.idea/vcs.xml
flask_vite/.idea/workspace.xml
flask_vite/__init__.py
flask_vite/cli.py
flask_vite/extension.py
flask_vite/npm.py
flask_vite/starter/.gitignore
flask_vite/starter/index.html
flask_vite/starter/main.js
flask_vite/starter/package-lock.json
flask_vite/starter/package.json
flask_vite/starter/postcss.config.js
flask_vite/starter/src/styles.css
flask_vite/starter/tailwind.config.js
flask_vite/starter/vite.config.js
flask_vite/starter/yarn.lock
flask_vite/tags.py
flask_vite-0.6.1.dist-info/RECORD
