Metadata-Version: 2.1
Name: flask-vite
Version: 0.6.1
Summary: Flask+Vite integration.
Author-Email: Abilian SAS <contact@abilian.com>
Classifier: Development Status :: 3 - Alpha
Classifier: Intended Audience :: Developers
Classifier: Natural Language :: English
Classifier: Programming Language :: Python :: 3
Classifier: Programming Language :: Python :: 3.9
Classifier: Programming Language :: Python :: 3.10
Classifier: Programming Language :: Python :: 3.11
Project-URL: homepage, https://github.com/abilian/flask-vite
Requires-Python: <4.0,>=3.9
Requires-Dist: flask>2
